openmc_data/__init__.py
openmc_data/_version.py
openmc_data/urls.py
openmc_data/urls_chain.py
openmc_data/urls_h5.py
openmc_data/urls_xml.py
openmc_data/utils.py
openmc_data/convert/__init__.py
openmc_data/convert/convert_endf.py
openmc_data/convert/convert_fendl.py
openmc_data/convert/convert_jeff32.py
openmc_data/convert/convert_jeff33.py
openmc_data/convert/convert_lib80x.py
openmc_data/convert/convert_mcnp70.py
openmc_data/convert/convert_mcnp71.py
openmc_data/convert/convert_tendl.py
openmc_data/depletion/__init__.py
openmc_data/depletion/add_branching_ratios.py
openmc_data/depletion/branching_ratios_pwr.json
openmc_data/depletion/branching_ratios_sfr.json
openmc_data/depletion/casl_chain.py
openmc_data/depletion/chain-nndc-b7.1.xml
openmc_data/depletion/chain_casl_pwr.xml
openmc_data/depletion/chain_casl_sfr.xml
openmc_data/depletion/chain_endf_b7.1.xml
openmc_data/depletion/chain_endf_b7.1_pwr.xml
openmc_data/depletion/chain_endf_b7.1_sfr.xml
openmc_data/depletion/chain_endf_b8.0.xml
openmc_data/depletion/chain_endf_b8.0_pwr.xml
openmc_data/depletion/chain_endf_b8.0_sfr.xml
openmc_data/depletion/chain_endfb71_pwr.xml
openmc_data/depletion/chain_endfb71_sfr.xml
openmc_data/depletion/generate_endf71_chain_casl.py
openmc_data/depletion/generate_endf_chain.py
openmc_data/depletion/generate_jeff_chain.py
openmc_data/depletion/generate_jendl_chain.py
openmc_data/depletion/generate_serpent_fissq.py
openmc_data/depletion/generate_tendl_chain.py
openmc_data/depletion/reduce_chain.py
openmc_data/depletion/serpent_fissq.json
openmc_data/depletion/tendl2019_nuclides.json
openmc_data/depletion/tendl2021_nuclides.json
openmc_data/download/__init__.py
openmc_data/download/download_chain.py
openmc_data/download/download_endf.py
openmc_data/download/download_tendl.py
openmc_data/generate/__init__.py
openmc_data/generate/generate_cendl.py
openmc_data/generate/generate_endf.py
openmc_data/generate/generate_fendl.py
openmc_data/generate/generate_jeff33.py
openmc_data-2.3.1.dist-info/licenses/LICENSE
openmc_data-2.3.1.dist-info/METADATA
openmc_data-2.3.1.dist-info/WHEEL
openmc_data-2.3.1.dist-info/entry_points.txt
openmc_data-2.3.1.dist-info/top_level.txt
openmc_data-2.3.1.dist-info/RECORD
