Metadata-Version: 2.4
Name: openmc_data
Version: 2.3.1
Summary: A Python package containing a collection of scripts for producing and downloading data for OpenMC
Author-email: Jonathan Shimwell <mail@jshimwell.com>
License: Copyright (c) 2019-2022 UChicago Argonne LLC and contributors
Project-URL: Homepage, https://github.com/fusion-energy/openmc_data
Project-URL: Bug Tracker, https://github.com/fusion-energy/openmc_data/issues
Keywords: openmc,nuclear,data,download,process,cross,section
Classifier: Programming Language :: Python :: 3
Classifier: License :: OSI Approved :: MIT License
Classifier: Operating System :: OS Independent
Requires-Python: >=3.8
License-File: LICENSE
Requires-Dist: numpy>=1.21.1
Provides-Extra: tests
Requires-Dist: pytest; extra == "tests"
Requires-Dist: requests; extra == "tests"
Dynamic: license-file
